igeFirebase.cp39-win_amd64.pyd
igeFirebase-0.2.0.dist-info/LICENSE
igeFirebase-0.2.0.dist-info/METADATA
igeFirebase-0.2.0.dist-info/WHEEL
igeFirebase-0.2.0.dist-info/top_level.txt
igeFirebase-0.2.0.dist-info/RECORD
