Metadata-Version: 2.1
Name: igeFirebase
Version: 0.2.0
Summary: C++ Firebase extension for 3D and 2D games.
Home-page: https://indigames.net/
Author: Indigames
Author-email: dev@indigames.net
License: MIT
Keywords: Firebase 3D game Indigames
Platform: UNKNOWN
Classifier: Intended Audience :: Developers
Classifier: License :: OSI Approved :: MIT License
Classifier: Programming Language :: Python :: 3
Classifier: Operating System :: Microsoft :: Windows
Classifier: Topic :: Games/Entertainment
